plover_emoji/__init__.py
plover_emoji/emoji-toolkit/emoji_strategy.json
plover_emoji-0.0.4.dist-info/LICENSE.txt
plover_emoji-0.0.4.dist-info/METADATA
plover_emoji-0.0.4.dist-info/WHEEL
plover_emoji-0.0.4.dist-info/entry_points.txt
plover_emoji-0.0.4.dist-info/top_level.txt
plover_emoji-0.0.4.dist-info/zip-safe
plover_emoji-0.0.4.dist-info/RECORD
